{
    "points": [
        {
            "P": [
                0.0,
                0.0,
                0.0
            ],
            "level_center": [
                4500,
                300.0,
                -500
            ],
            "rot": 0.0,
            "struct": "/Game/Maps/Datas/Data_Design/Chapter01/Chapter01_Sew_Enter_01",
            "enterLevel": 1,
            "exitLevel": 0,
            "door": [
                {
                    "door_name": "BP_Arrow",
                    "door_state": 1,
                    "if_door": 1,
                    "near_door": "BP_Arrow2",
                    "next_id": 1
                }
            ],
            "if_layout": 0,
            "art_path": "",
            "id": 0
        },
        {
            "P": [
                -12578.251647949219,
                118.59130859375,
                1843.2624816894531
            ],
            "level_center": [
                -3500,
                300.0,
                500
            ],
            "rot": -90.00000762939453,
            "struct": "/Game/Maps/Datas/Data_Design/Chapter01/Chapter01_Sew_Connector_02",
            "enterLevel": 0,
            "exitLevel": 0,
            "door": [
                {
                    "door_name": "BP_Arrow3",
                    "door_state": 1,
                    "if_door": 1,
                    "near_door": "BP_Arrow4",
                    "next_id": 2
                },
                {
                    "door_name": "BP_Arrow2",
                    "door_state": 0,
                    "if_door": 0,
                    "near_door": "BP_Arrow",
                    "next_id": 0
                },
                {
                    "door_name": "BP_Arrow",
                    "door_state": 0,
                    "if_door": 1,
                    "near_door": "",
                    "next_id": -1
                }
            ],
            "if_layout": 0,
            "art_path": "",
            "id": 1
        },
        {
            "P": [
                -9281.550598144531,
                -2129.1587829589844,
                14730.363464355469
            ],
            "level_center": [
                1500,
                400.0,
                -500
            ],
            "rot": 89.99999237060547,
            "struct": "/Game/Maps/Datas/Data_Design/Chapter01/Chapter01_Sew_Road_01",
            "enterLevel": 0,
            "exitLevel": 0,
            "door": [
                {
                    "door_name": "BP_Arrow",
                    "door_state": 0,
                    "if_door": 1,
                    "near_door": "",
                    "next_id": -1
                },
                {
                    "door_name": "BP_Arrow2",
                    "door_state": 0,
                    "if_door": 1,
                    "near_door": "",
                    "next_id": -1
                },
                {
                    "door_name": "BP_Arrow3",
                    "door_state": 1,
                    "if_door": 1,
                    "near_door": "BP_Arrow3",
                    "next_id": 3
                },
                {
                    "door_name": "BP_Arrow4",
                    "door_state": 0,
                    "if_door": 0,
                    "near_door": "BP_Arrow3",
                    "next_id": 1
                }
            ],
            "if_layout": 0,
            "art_path": "",
            "id": 2
        },
        {
            "P": [
                7651.499938964844,
                -480.8086395263672,
                14130.960083007812
            ],
            "level_center": [
                -6500,
                2100.0001907348633,
                4500
            ],
            "rot": -90.00001525878906,
            "struct": "/Game/Maps/Datas/Data_Design/Chapter01/Chapter01_Sew_Enter_02",
            "enterLevel": 0,
            "exitLevel": 0,
            "door": [
                {
                    "door_name": "BP_Arrow",
                    "door_state": 1,
                    "if_door": 1,
                    "near_door": "BP_Arrow",
                    "next_id": 4
                },
                {
                    "door_name": "BP_Arrow2",
                    "door_state": 0,
                    "if_door": 1,
                    "near_door": "",
                    "next_id": -1
                },
                {
                    "door_name": "BP_Arrow3",
                    "door_state": 0,
                    "if_door": 0,
                    "near_door": "BP_Arrow3",
                    "next_id": 2
                }
            ],
            "if_layout": 0,
            "art_path": "",
            "id": 3
        },
        {
            "P": [
                8435.877227783203,
                -1080.2093505859375,
                29930.38330078125
            ],
            "level_center": [
                4500,
                1700.0,
                -3500
            ],
            "rot": -90.0000228881836,
            "struct": "/Game/Maps/Datas/Data_Design/Chapter01/Chapter01_Sew_Exit_01",
            "enterLevel": 0,
            "exitLevel": 1,
            "door": [
                {
                    "door_name": "BP_Arrow",
                    "door_state": 0,
                    "if_door": 0,
                    "near_door": "BP_Arrow",
                    "next_id": 3
                }
            ],
            "if_layout": 0,
            "art_path": "",
            "id": 4
        }
    ],
    "attr": [
        {
            "1000000001_id": 2,
            "1000000001_struct": "/Game/Maps/Datas/Data_Design/Chapter01/Chapter01_Sew_Road_01"
        },
        {
            "1000000002_id": 13,
            "1000000002_struct": "/Game/Maps/Datas/Data_Design/Chapter01/Chapter01_Sew_Road_01"
        },
        {
            "1000000003_id": 12,
            "1000000003_struct": "/Game/Maps/Datas/Data_Design/Chapter01/Chapter01_Sew_Road_01"
        }
    ]
}