{
    "points": [
        {
            "P": [
                0.0,
                0.0,
                0.0
            ],
            "level_center": [
                -2500,
                5820.99951171875,
                -3500
            ],
            "rot": -450.0,
            "struct": "/Game/Maps/Datas/Data_Design/Chapter01/Chapter01_Kuangkeng_Enter_03",
            "enterLevel": 1,
            "exitLevel": 0,
            "door": [
                {
                    "door_name": "BP_Arrow",
                    "door_state": 1,
                    "if_door": 1,
                    "near_door": "BP_Arrow",
                    "next_id": 12
                },
                {
                    "door_name": "BP_Arrow2",
                    "door_state": 1,
                    "if_door": 1,
                    "near_door": "BP_Arrow2",
                    "next_id": 1
                },
                {
                    "door_name": "BP_Arrow3",
                    "door_state": 1,
                    "if_door": 1,
                    "near_door": "BP_Arrow",
                    "next_id": 13
                }
            ],
            "if_layout": 0,
            "art_path": "/Game/Maps/Datas/Data_Art/Chapter01/Chapter01_Kuangkeng_Enter_02_Art",
            "id": 0
        },
        {
            "P": [
                15000.0,
                -4320.9991455078125,
                -100.00152587890625
            ],
            "level_center": [
                0,
                1500.0,
                0
            ],
            "rot": -180.00001525878906,
            "struct": "/Game/Maps/Datas/Data_Design/Chapter01/Chapter01_Kuangkeng_Road_08",
            "enterLevel": 0,
            "exitLevel": 0,
            "door": [
                {
                    "door_name": "BP_Arrow",
                    "door_state": 1,
                    "if_door": 1,
                    "near_door": "BP_Arrow3",
                    "next_id": 7
                },
                {
                    "door_name": "BP_Arrow2",
                    "door_state": 0,
                    "if_door": 0,
                    "near_door": "BP_Arrow2",
                    "next_id": 0
                },
                {
                    "door_name": "BP_Arrow3",
                    "door_state": 1,
                    "if_door": 1,
                    "near_door": "BP_Arrow",
                    "next_id": 2
                }
            ],
            "if_layout": 0,
            "art_path": "",
            "id": 1
        },
        {
            "P": [
                20299.99542236328,
                -3650.9994506835938,
                -12400.003051757812
            ],
            "level_center": [
                1500,
                3769.9996948242188,
                1500
            ],
            "rot": -90.0000228881836,
            "struct": "/Game/Maps/Datas/Data_Design/Chapter01/Chapter01_Kuangkeng_Road_11",
            "enterLevel": 0,
            "exitLevel": 0,
            "door": [
                {
                    "door_name": "BP_Arrow",
                    "door_state": 0,
                    "if_door": 0,
                    "near_door": "BP_Arrow3",
                    "next_id": 1
                },
                {
                    "door_name": "BP_Arrow2",
                    "door_state": 1,
                    "if_door": 0,
                    "near_door": "BP_Arrow3",
                    "next_id": 3
                },
                {
                    "door_name": "BP_Arrow3",
                    "door_state": 1,
                    "if_door": 1,
                    "near_door": "BP_Arrow",
                    "next_id": 11
                }
            ],
            "if_layout": 0,
            "art_path": "",
            "id": 2
        },
        {
            "P": [
                17999.99237060547,
                -4820.9991455078125,
                -24200.003051757812
            ],
            "level_center": [
                -500,
                800.0,
                -1500
            ],
            "rot": -0.0,
            "struct": "/Game/Maps/Datas/Data_Design/Chapter01/Chapter01_Kuangkeng_Road_04",
            "enterLevel": 0,
            "exitLevel": 0,
            "door": [
                {
                    "door_name": "BP_Arrow",
                    "door_state": 1,
                    "if_door": 1,
                    "near_door": "BP_Arrow",
                    "next_id": 4
                },
                {
                    "door_name": "BP_Arrow2",
                    "door_state": 1,
                    "if_door": 1,
                    "near_door": "BP_Arrow",
                    "next_id": 10
                },
                {
                    "door_name": "BP_Arrow3",
                    "door_state": 0,
                    "if_door": 0,
                    "near_door": "BP_Arrow2",
                    "next_id": 2
                }
            ],
            "if_layout": 0,
            "art_path": "",
            "id": 3
        },
        {
            "P": [
                18939.993286132812,
                -2953.9993286132812,
                -35200.00305175781
            ],
            "level_center": [
                500,
                1167.0000076293945,
                -500
            ],
            "rot": 90.00000762939453,
            "struct": "/Game/Maps/Datas/Data_Design/Chapter01/Chapter01_Kuangkeng_Exit_01",
            "enterLevel": 0,
            "exitLevel": 1,
            "door": [
                {
                    "door_name": "BP_Arrow",
                    "door_state": 0,
                    "if_door": 0,
                    "near_door": "BP_Arrow",
                    "next_id": 3
                },
                {
                    "door_name": "BP_Arrow2",
                    "door_state": 1,
                    "if_door": 1,
                    "near_door": "BP_Arrow",
                    "next_id": 9
                }
            ],
            "if_layout": 0,
            "art_path": "",
            "id": 4
        },
        {
            "P": [
                16540.687561035156,
                -5290.999603271484,
                14800.0
            ],
            "level_center": [
                -500,
                -20.000076293945312,
                -3500
            ],
            "rot": 180.00001525878906,
            "struct": "/Game/Maps/Datas/Data_Design/Chapter01/Chapter01_Kuangkeng_Road_05",
            "enterLevel": 0,
            "exitLevel": 0,
            "door": [
                {
                    "door_name": "BP_Arrow",
                    "door_state": 1,
                    "if_door": 1,
                    "near_door": "BP_Arrow",
                    "next_id": 8
                },
                {
                    "door_name": "BP_Arrow2",
                    "door_state": 1,
                    "if_door": 1,
                    "near_door": "BP_Arrow",
                    "next_id": 14
                },
                {
                    "door_name": "BP_Arrow3",
                    "door_state": 0,
                    "if_door": 0,
                    "near_door": "BP_Arrow",
                    "next_id": 1
                }
            ],
            "if_layout": 0,
            "art_path": "",
            "id": 7
        },
        {
            "P": [
                26190.689086914062,
                -5520.9991455078125,
                15213.986206054688
            ],
            "level_center": [
                -500,
                0.0,
                -500
            ],
            "rot": -0.0,
            "struct": "/Game/Maps/Datas/Data_Design/Chapter01/Chapter01_Kuangkeng_Road_02",
            "enterLevel": 0,
            "exitLevel": 0,
            "door": [
                {
                    "door_name": "BP_Arrow",
                    "door_state": 0,
                    "if_door": 0,
                    "near_door": "BP_Arrow",
                    "next_id": 7
                },
                {
                    "door_name": "BP_Arrow2",
                    "door_state": 1,
                    "if_door": 1,
                    "near_door": "BP_Arrow",
                    "next_id": 15
                },
                {
                    "door_name": "BP_Arrow3",
                    "door_state": 1,
                    "if_door": 1,
                    "near_door": "BP_Arrow",
                    "next_id": 16
                }
            ],
            "if_layout": 0,
            "art_path": "",
            "id": 8
        },
        {
            "P": [
                23899.993896484375,
                -2550.9994506835938,
                -35930.00183105469
            ],
            "level_center": [
                500,
                0.0,
                0
            ],
            "rot": -89.99999237060547,
            "struct": "/Game/Maps/Datas/Data_Design/Chapter01/Chapter01_Kuangkeng_DeadEnd_03",
            "enterLevel": 0,
            "exitLevel": 0,
            "door": [
                {
                    "door_name": "BP_Arrow",
                    "door_state": 0,
                    "if_door": 0,
                    "near_door": "BP_Arrow2",
                    "next_id": 4
                }
            ],
            "if_layout": 0,
            "art_path": "",
            "id": 9
        },
        {
            "P": [
                11549.992370605469,
                -4800.999450683594,
                -24300.003051757812
            ],
            "level_center": [
                500,
                0.0,
                500
            ],
            "rot": 90.00000762939453,
            "struct": "/Game/Maps/Datas/Data_Design/Chapter01/Chapter01_Kuangkeng_DeadEnd_01",
            "enterLevel": 0,
            "exitLevel": 0,
            "door": [
                {
                    "door_name": "BP_Arrow",
                    "door_state": 0,
                    "if_door": 0,
                    "near_door": "BP_Arrow2",
                    "next_id": 3
                }
            ],
            "if_layout": 0,
            "art_path": "",
            "id": 10
        },
        {
            "P": [
                26749.996948242188,
                -3400.9994506835938,
                -10500.006103515625
            ],
            "level_center": [
                500,
                0.0,
                500
            ],
            "rot": -90.00003051757812,
            "struct": "/Game/Maps/Datas/Data_Design/Chapter01/Chapter01_Kuangkeng_DeadEnd_01",
            "enterLevel": 0,
            "exitLevel": 0,
            "door": [
                {
                    "door_name": "BP_Arrow",
                    "door_state": 0,
                    "if_door": 0,
                    "near_door": "BP_Arrow3",
                    "next_id": 2
                }
            ],
            "if_layout": 0,
            "art_path": "",
            "id": 11
        },
        {
            "P": [
                5300.000381469727,
                -4820.999526977539,
                -12300.0
            ],
            "level_center": [
                500,
                400.0,
                500
            ],
            "rot": 90.00001525878906,
            "struct": "/Game/Maps/Datas/Data_Design/Chapter01/Chapter01_Kuangkeng_DeadEnd_04",
            "enterLevel": 0,
            "exitLevel": 0,
            "door": [
                {
                    "door_name": "BP_Arrow",
                    "door_state": 0,
                    "if_door": 0,
                    "near_door": "BP_Arrow",
                    "next_id": 0
                }
            ],
            "if_layout": 0,
            "art_path": "",
            "id": 12
        },
        {
            "P": [
                2199.9998092651367,
                -3620.999526977539,
                12300.0
            ],
            "level_center": [
                500,
                400.0,
                500
            ],
            "rot": -89.99999237060547,
            "struct": "/Game/Maps/Datas/Data_Design/Chapter01/Chapter01_Kuangkeng_DeadEnd_04",
            "enterLevel": 0,
            "exitLevel": 0,
            "door": [
                {
                    "door_name": "BP_Arrow",
                    "door_state": 0,
                    "if_door": 0,
                    "near_door": "BP_Arrow3",
                    "next_id": 0
                }
            ],
            "if_layout": 0,
            "art_path": "",
            "id": 13
        },
        {
            "P": [
                9990.687561035156,
                -5800.999450683594,
                15283.982849121094
            ],
            "level_center": [
                500,
                0.0,
                500
            ],
            "rot": 90.0000228881836,
            "struct": "/Game/Maps/Datas/Data_Design/Chapter01/Chapter01_Kuangkeng_DeadEnd_01",
            "enterLevel": 0,
            "exitLevel": 0,
            "door": [
                {
                    "door_name": "BP_Arrow",
                    "door_state": 0,
                    "if_door": 0,
                    "near_door": "BP_Arrow2",
                    "next_id": 7
                }
            ],
            "if_layout": 0,
            "art_path": "",
            "id": 14
        },
        {
            "P": [
                31590.692138671875,
                -5500.999450683594,
                15813.980102539062
            ],
            "level_center": [
                500,
                0.0,
                500
            ],
            "rot": -90.00000762939453,
            "struct": "/Game/Maps/Datas/Data_Design/Chapter01/Chapter01_Kuangkeng_DeadEnd_01",
            "enterLevel": 0,
            "exitLevel": 0,
            "door": [
                {
                    "door_name": "BP_Arrow",
                    "door_state": 0,
                    "if_door": 0,
                    "near_door": "BP_Arrow2",
                    "next_id": 8
                }
            ],
            "if_layout": 0,
            "art_path": "",
            "id": 15
        },
        {
            "P": [
                26940.545654296875,
                -5520.7000732421875,
                9222.972106933594
            ],
            "level_center": [
                500,
                400.0,
                500
            ],
            "rot": 90.00000762939453,
            "struct": "/Game/Maps/Datas/Data_Design/Chapter01/Chapter01_Kuangkeng_DeadEnd_04",
            "enterLevel": 0,
            "exitLevel": 0,
            "door": [
                {
                    "door_name": "BP_Arrow",
                    "door_state": 0,
                    "if_door": 0,
                    "near_door": "BP_Arrow3",
                    "next_id": 8
                }
            ],
            "if_layout": 0,
            "art_path": "",
            "id": 16
        }
    ],
    "attr": [
        {
            "1000000001_id": 8,
            "1000000001_struct": "/Game/Maps/Datas/Data_Design/Chapter01/Chapter01_Kuangkeng_Road_02"
        },
        {
            "1000000002_id": 1,
            "1000000002_struct": "/Game/Maps/Datas/Data_Design/Chapter01/Chapter01_Kuangkeng_Road_08"
        },
        {
            "1000000003_id": 7,
            "1000000003_struct": "/Game/Maps/Datas/Data_Design/Chapter01/Chapter01_Kuangkeng_Road_05"
        }
    ]
}