{
    "points": [
        {
            "P": [
                0.0,
                0.0,
                0.0
            ],
            "level_center": [
                1500,
                3141.999755859375,
                -4500
            ],
            "rot": -0.0,
            "struct": "/Game/Maps/Datas/Data_Design/Prologue/Prologue_Enter_02",
            "enterLevel": 1,
            "exitLevel": 0,
            "door": [
                {
                    "door_name": "BP_Arrow",
                    "door_state": 1,
                    "if_door": 1,
                    "near_door": "BP_Arrow",
                    "next_id": 1
                },
                {
                    "door_name": "BP_Arrow2",
                    "door_state": 0,
                    "if_door": 1,
                    "near_door": "",
                    "next_id": -1
                },
                {
                    "door_name": "BP_Arrow3",
                    "door_state": 0,
                    "if_door": 1,
                    "near_door": "",
                    "next_id": -1
                }
            ],
            "if_layout": 1,
            "art_path": "/Game/Maps/Datas/Data_Art/Prologue/Prologue_Road_06_Art",
            "id": 0
        },
        {
            "P": [
                -972.9386329650879,
                -2616.6927337646484,
                -7999.578857421875
            ],
            "level_center": [
                500,
                281.0000419616699,
                500
            ],
            "rot": 90.00000762939453,
            "struct": "/Game/Maps/Datas/Data_Design/Prologue/Prologue_Connector_02",
            "enterLevel": 0,
            "exitLevel": 0,
            "door": [
                {
                    "door_name": "BP_Arrow",
                    "door_state": 0,
                    "if_door": 0,
                    "near_door": "BP_Arrow",
                    "next_id": 0
                },
                {
                    "door_name": "BP_Arrow2",
                    "door_state": 1,
                    "if_door": 1,
                    "near_door": "BP_Arrow",
                    "next_id": 2
                }
            ],
            "if_layout": 1,
            "art_path": "",
            "id": 1
        },
        {
            "P": [
                -916.339111328125,
                -1215.7325744628906,
                -18476.287841796875
            ],
            "level_center": [
                1500,
                2369.9996948242188,
                2500
            ],
            "rot": -180.00001525878906,
            "struct": "/Game/Maps/Datas/Data_Design/Prologue/Prologue_Road_15",
            "enterLevel": 0,
            "exitLevel": 0,
            "door": [
                {
                    "door_name": "BP_Arrow",
                    "door_state": 0,
                    "if_door": 0,
                    "near_door": "BP_Arrow2",
                    "next_id": 1
                },
                {
                    "door_name": "BP_Arrow2",
                    "door_state": 1,
                    "if_door": 1,
                    "near_door": "BP_Arrow2",
                    "next_id": 3
                },
                {
                    "door_name": "BP_Arrow3",
                    "door_state": 0,
                    "if_door": 1,
                    "near_door": "",
                    "next_id": -1
                }
            ],
            "if_layout": 0,
            "art_path": "",
            "id": 2
        },
        {
            "P": [
                9899.925994873047,
                666.4810180664062,
                -23453.062438964844
            ],
            "level_center": [
                -500,
                3758.9996337890625,
                7500
            ],
            "rot": 180.00001525878906,
            "struct": "/Game/Maps/Datas/Data_Design/Prologue/Prologue_Exit_02",
            "enterLevel": 0,
            "exitLevel": 1,
            "door": [
                {
                    "door_name": "BP_Arrow",
                    "door_state": 0,
                    "if_door": 1,
                    "near_door": "",
                    "next_id": -1
                },
                {
                    "door_name": "BP_Arrow2",
                    "door_state": 0,
                    "if_door": 0,
                    "near_door": "BP_Arrow2",
                    "next_id": 2
                },
                {
                    "door_name": "BP_Arrow3",
                    "door_state": 0,
                    "if_door": 1,
                    "near_door": "",
                    "next_id": -1
                }
            ],
            "if_layout": 1,
            "art_path": "",
            "id": 3
        }
    ]
}